piltextbox/__init__.py
piltextbox/_constants.py
piltextbox/textbox/TextBox.py
piltextbox/textbox/__init__.py
piltextbox/textbox/formatting/__init__.py
piltextbox/textbox/formatting/formatparser.py
piltextbox-0.2.1.dist-info/LICENSE.txt
piltextbox-0.2.1.dist-info/METADATA
piltextbox-0.2.1.dist-info/WHEEL
piltextbox-0.2.1.dist-info/top_level.txt
piltextbox-0.2.1.dist-info/RECORD
