Metadata-Version: 2.1
Name: piltextbox
Version: 0.2.1
Summary: Streamlined text writing on images, using the Pillow (PIL) library
Home-page: https://github.com/JamesPImes/piltextbox
Author: James P. Imes
Author-email: jamesimes@gmail.com
License: MIT
Platform: UNKNOWN
